{
    "info": {
        "id": "sb/10/66/4",
        "prevId": "sb/10/66/3",
        "nextId": "sb/10/66/5"
    },
    "verses": [
        {
            "roman": "dūtas tu dvārakām etya\nsabhāyām āsthitaṁ prabhum\nkṛṣṇaṁ kamala-patrākṣaṁ\nrāja-sandeśam abravīt\n"
        }
    ],
    "synonyms": "dūtaḥ—the messenger; tu—then; dvārakām—at Dvārakā; etya—arriving; sabhāyām—in the royal assembly; āsthitam—present; prabhum—to the almighty Lord; kṛṣṇam—Kṛṣṇa; kamala—of a lotus; patra—(like) the petals; akṣam—whose eyes; rāja—of his King; sandeśam—the message; abravīt—spoke.",
    "translation": "Arriving in Dvārakā, the messenger found lotus-eyed Kṛṣṇa in His royal assembly and relayed the King's message to that almighty Lord.",
    "purport": null
}
