{
    "info": {
        "id": "sb/10/61/39",
        "prevId": "sb/10/61/38",
        "nextId": "sb/10/61/40"
    },
    "verses": [
        {
            "roman": "nihate rukmiṇi śyāle\nnābravīt sādhv asādhu vā\nrakmiṇī-balayo rājan\nsneha-bhaṅga-bhayād dhariḥ\n"
        }
    ],
    "synonyms": "nihate—being killed; rukmiṇi—Rukmī; śyāle—His brother-in-law; na abravīt—did not say; sādhu—good; asādhu—not good; vā—or; rukmiṇī-balayoḥ—of Rukmiṇī and Balarāma; rājan—O King; sneha—the affection; bhaṅga—of breaking; bhayāt—out of fear; hariḥ—Lord Kṛṣṇa.",
    "translation": "When His brother-in-law Rukmī was slain, Lord Kṛṣṇa neither applauded nor protested, O King, for He feared jeopardizing His affectionate ties with either Rukmiṇī or Balarāma.",
    "purport": null
}
