{
    "info": {
        "id": "sb/10/88/22",
        "prevId": "sb/10/88/21",
        "nextId": "sb/10/88/23"
    },
    "verses": [
        {
            "roman": "tac chrutvā bhagavān rudro\ndurmanā iva bhārata\noṁ iti prahasaṁs tasmai\ndade 'her amṛtaṁ yathā\n"
        }
    ],
    "synonyms": "tat—this; śrutvā—hearing; bhagavān rudraḥ—Lord Rudra; durmanāḥ—displeased; iva—as if; bhārata—O descendant of Bharata; oṁ iti—vibrating the sacred syllable oṁ as a sign of assent; prahasan—smiling broadly; tasmai—to him; dade—he gave it; aheḥ—to a snake; amṛtam—nectar; yathā—as.",
    "translation": "Upon hearing this, Lord Rudra seemed somewhat disturbed. Nonetheless, O descendant of Bharata, he vibrated oṁ to signify his assent, granting Vṛka the benediction with an ironic smile, as if giving milk to a poisonous snake.",
    "purport": null
}
