{
    "info": {
        "id": "sb/8/10/3",
        "prevId": "sb/8/10/2",
        "nextId": "sb/8/10/4"
    },
    "verses": [
        {
            "roman": "sapatnānāṁ parām ṛddhiṁ\ndṛṣṭvā te diti-nandanāḥ\namṛṣyamāṇā utpetur\ndevān pratyudyatāyudhāḥ\n"
        }
    ],
    "synonyms": "sapatnānām—of their rivals, the demigods; parām—the best; ṛddhim—opulence; dṛṣṭvā—observing; te—all of them; diti-nandanāḥ—the sons of Diti, the Daityas; amṛṣyamāṇāḥ—being intolerant; utpetuḥ—ran toward (just to create a disturbance); devān—the demigods; pratyudyata-āyudhāḥ—their weapons raised.",
    "translation": "Seeing the victory of the demigods, the demons became intolerant of their superior opulence. Thus they began to march toward the demigods with raised weapons.",
    "purport": null
}
