{
    "info": {
        "id": "sb/8/10/8",
        "prevId": "sb/8/10/7",
        "nextId": "sb/8/10/9"
    },
    "verses": [
        {
            "roman": "rathino rathibhis tatra\npattibhiḥ saha pattayaḥ\nhayā hayair ibhāś cebhaiḥ\nsamasajjanta saṁyuge\n"
        }
    ],
    "synonyms": "rathinaḥ—fighters on chariots; rathibhiḥ—with the charioteers of the enemy; tatra—in the battlefield; pattibhiḥ—with the infantry soldiers; saha—with; pattayaḥ—the infantry of the enemy soldiers; hayāḥ—the horses; hayaiḥ—with the enemy's soldiers; ibhāḥ—the soldiers fighting on the backs of elephants; ca—and; ibhaiḥ—with the enemy's soldiers on the backs of elephants; samasajjanta—began to fight together on an equal level; saṁyuge—on the battlefield.",
    "translation": "\nOn that battlefield, the charioteers fought with the opposing charioteers, the infantry soldiers with the opposing infantry, the soldiers on horseback with the opposing soldiers on horseback, and the soldiers on the backs of elephants with the enemy soldiers on elephants. In this way, the fighting took place between equals.\n\n",
    "purport": null
}
