{
    "info": {
        "id": "sb/9/2/19",
        "prevId": "sb/9/2/18",
        "nextId": "sb/9/2/20"
    },
    "verses": [
        {
            "roman": "citraseno nariṣyantād\nṛkṣas tasya suto 'bhavat\ntasya mīḍhvāṁs tataḥ pūrṇa\nindrasenas tu tat-sutaḥ\n"
        }
    ],
    "synonyms": "citrasenaḥ—one named Citrasena; nariṣyantāt—from Nariṣyanta, another son of Manu; ṛkṣaḥ—Ṛkṣa; tasya—of Citrasena; sutaḥ—the son; abhavat—became; tasya—of him (Ṛkṣa); mīḍhvān—Mīḍhvān; tataḥ—from him (Mīḍhvān); pūrṇaḥ—Pūrṇa; indrasenaḥ—Indrasena; tu—but; tat-sutaḥ—the son of him (Pūrṇa).",
    "translation": "From Nariṣyanta came a son named Citrasena and from him a son named Ṛkṣa. From Ṛkṣa came Mīḍhvān, from Mīḍhvān came Pūrṇa, and from Pūrṇa came Indrasena.",
    "purport": null
}
