{
    "info": {
        "id": "sb/9/2/34",
        "prevId": "sb/9/2/33",
        "nextId": "sb/9/2/35-36"
    },
    "verses": [
        {
            "roman": "hemacandraḥ sutas tasya\ndhūmrākṣas tasya cātmajaḥ\ntat-putrāt saṁyamād āsīt\nkṛśāśvaḥ saha-devajaḥ\n"
        }
    ],
    "synonyms": "hemacandraḥ—was named Hemacandra; sutaḥ—the son; tasya—of him (Viśāla); dhūmrākṣaḥ—was named Dhūmrākṣa; tasya—of him (Hemacandra); ca—also; ātmajaḥ—the son; tat-putrāt—from the son of him (Dhūmrākṣa); saṁyamāt—from he who was named Saṁyama; āsīt—there was; kṛśāśvaḥ—Kṛśāśva; saha—along with; devajaḥ—Devaja.",
    "translation": "The son of Viśāla was known as Hemacandra, his son was Dhūmrākṣa, and his son was Saṁyama, whose sons were Devaja and Kṛśāśva.",
    "purport": null
}
