{
    "info": {
        "id": "sb/10/55/17",
        "prevId": "sb/10/55/16",
        "nextId": "sb/10/55/18"
    },
    "verses": [
        {
            "roman": "sa ca śambaram abhyetya\nsaṁyugāya samāhvayat\naviṣahyais tam ākṣepaiḥ\nkṣipan sañjanayan kalim\n"
        }
    ],
    "synonyms": "saḥ—He; ca—and; śambaram—Śambara; abhyetya—approaching; saṁyugāya—to battle; samāhvayat—called him; aviṣahyaiḥ—intolerable; tam—him; ākṣepaiḥ—with insults; kṣipan—reviling; sañjanayan—inciting; kalim—a fight.",
    "translation": "Pradyumna approached Śambara and called him to battle, hurling intolerable insults at him to foment a conflict.",
    "purport": null
}
