{
    "info": {
        "id": "sb/10/86/56",
        "prevId": "sb/10/86/55",
        "nextId": "sb/10/86/57"
    },
    "verses": [
        {
            "roman": "carācaram idaṁ viśvaṁ\nbhāvā ye cāsya hetavaḥ\nmad-rūpāṇīti cetasy\nādhatte vipro mad-īkṣayā\n"
        }
    ],
    "synonyms": "cara—moving; acaram—and nonmoving; idam—this; viśvam—universe; bhāvāḥ—elemental categories; ye—which; ca—and; asya—its; hetavaḥ—sources; mat—My; rūpāṇi—forms; iti—such a thought; cetasi—within his mind; ādhatte—maintains; vipraḥ—a brāhmaṇa; mat—of Me; īkṣayā—by his perception.",
    "translation": "Because he has realized Me, a brāhmaṇa is firmly fixed in the knowledge that everything moving and nonmoving in the universe, and also the primary elements of its creation, are all manifest forms expanded from Me.",
    "purport": null
}
