{
    "info": {
        "id": "sb/10/89/37",
        "prevId": "sb/10/89/36",
        "nextId": "sb/10/89/38"
    },
    "verses": [
        {
            "roman": "nyaruṇat sūtikāgāraṁ\nśarair nānāstra-yojitaiḥ\ntiryag ūrdhvam adhaḥ pārthaś\ncakāra śara-pañjaram\n"
        }
    ],
    "synonyms": "nyaruṇat—he enveloped; sūtikā-āgāram—the house where the birth was taking place; śaraiḥ—with arrows; nānā—various; astra—to missiles; yojitaiḥ—attached; tiryak—horizontally; ūrdhvam—upwards; adhaḥ—downwards; pārthaḥ—Arjuna; cakāra—made; śara—of arrows; pañjaram—a cage.",
    "translation": "Arjuna fenced in the house where the birth was taking place by shooting arrows attached to various missiles. Thus the son of Pṛthā constructed a protective cage of arrows, covering the house upwards, downwards and sideways.",
    "purport": null
}
