{
    "info": {
        "id": "sb/10/64/17",
        "prevId": "sb/10/64/16",
        "nextId": "sb/10/64/18"
    },
    "verses": [
        {
            "roman": "tāṁ nīyamānāṁ tat-svāmī\ndṛṣṭvovāca mameti tam\nmameti parigrāhy āha\nnṛgo me dattavān iti\n"
        }
    ],
    "synonyms": "tām—she, the cow; nīyamānām—being led away; tat—her; svāmī—master; dṛṣṭvā—seeing; uvāca—said; mama—mine; iti—thus; tam—to him; mama—mine; iti—thus; parigrāhī—he who had accepted the gift; āha—said; nṛgaḥ—King Nṛga; me—to me; dattavān—gave; iti—thus.",
    "translation": "\nWhen the cow's first owner saw her being led away, he said, \"She is mine!\" The second brāhmaṇa, who had accepted her as a gift, replied, \"No, she's mine! Nṛga gave her to me.\"\n\n",
    "purport": null
}
