{
    "info": {
        "id": "sb/6/1/43",
        "prevId": "sb/6/1/42",
        "nextId": "sb/6/1/44"
    },
    "verses": [
        {
            "roman": "etair adharmo vijñātaḥ\nsthānaṁ daṇḍasya yujyate\nsarve karmānurodhena\ndaṇḍam arhanti kāriṇaḥ\n"
        }
    ],
    "synonyms": "etaiḥ—by all these (witnesses, beginning from the sun-god); adharmaḥ—deviation from the regulative principles; vijñātaḥ—is known; sthānam—the proper place; daṇḍasya—of punishment; yujyate—is accepted as; sarve—all; karma-anurodhena—with consideration of the activities performed; daṇḍam—punishment; arhanti—deserve; kāriṇaḥ—the performers of sinful activities.",
    "translation": "\n<b>The candidates for punishment are those who are confirmed by these many witnesses to have deviated from their prescribed regulative duties. Everyone engaged in fruitive activities is suitable to be subjected to punishment according to his sinful acts.</b>\n\n",
    "purport": null
}
