{
    "info": {
        "id": "sb/10/4/44",
        "prevId": "sb/10/4/43",
        "nextId": "sb/10/4/45"
    },
    "verses": [
        {
            "roman": "sandiśya sādhu-lokasya\nkadane kadana-priyān\nkāma-rūpa-dharān dikṣu\ndānavān gṛham āviśat\n"
        }
    ],
    "synonyms": "sandiśya—after giving permission; sādhu-lokasya—of the saintly persons; kadane—in persecution; kadana-priyān—to the demons, who were very expert at persecuting others; kāma-rūpa-dharān—who could assume any form, according to their own desire; dikṣu—in all directions; dānavān—to the demons; gṛham āviśat—Kaṁsa entered his own palace.",
    "translation": "\nThese demons, the followers of Kaṁsa, were expert at persecuting others, especially the Vaiṣṇavas, and could assume any form they desired. After giving these demons permission to go everywhere and persecute the saintly persons, Kaṁsa entered his palace.\n\n",
    "purport": null
}
