{
    "info": {
        "id": "sb/9/1/4",
        "prevId": "sb/9/1/2-3",
        "nextId": "sb/9/1/5"
    },
    "verses": [
        {
            "roman": "teṣāṁ vaṁśaṁ pṛthag brahman\nvaṁśānucaritāni ca\nkīrtayasva mahā-bhāga\nnityaṁ śuśrūṣatāṁ hi naḥ\n"
        }
    ],
    "synonyms": "teṣām—of all those kings; vaṁśam—the dynasties; pṛthak—separately; brahman—O great brāhmaṇa (Śukadeva Gosvāmī); vaṁśa-anucaritāni ca—and their dynasties and characteristics; kīrtayasva—kindly describe; mahā-bhāga—O greatly fortunate one; nityam—eternally; śuśrūṣatām—who are engaged in your service; hi—indeed; naḥ—of ourselves.",
    "translation": "O greatly fortunate Śukadeva Gosvāmī, O great brāhmaṇa, kindly describe to us separately the dynasties and characteristics of all those kings, for we are always eager to hear such topics from you.",
    "purport": null
}
