{
    "info": {
        "id": "sb/9/16/10",
        "prevId": "sb/9/16/9",
        "nextId": "sb/9/16/11"
    },
    "verses": [
        {
            "roman": "ekadāśramato rāme\nsabhrātari vanaṁ gate\nvairaṁ siṣādhayiṣavo\nlabdha-cchidrā upāgaman\n"
        }
    ],
    "synonyms": "ekadā—once upon a time; āśramataḥ—from the āśrama of Jamadagni; rāme—when Lord Paraśurāma; sa-bhrātari—with his brothers; vanam—into the forest; gate—having gone; vairam—revenge for past enmity; siṣādhayiṣavaḥ—desiring to fulfill; labdha-chidrāḥ—taking the opportunity; upāgaman—they came near the residence of Jamadagni.",
    "translation": "Once when Paraśurāma left the āśrama for the forest with Vasumān and his other brothers, the sons of Kārtavīryārjuna took the opportunity to approach Jamadagni's residence to seek vengeance for their grudge.",
    "purport": null
}
