{
    "info": {
        "id": "sb/10/25/25",
        "prevId": "sb/10/25/24",
        "nextId": "sb/10/25/26"
    },
    "verses": [
        {
            "roman": "khaṁ vyabhram uditādityaṁ\nvāta-varṣaṁ ca dāruṇam\nniśamyoparataṁ gopān\ngovardhana-dharo 'bravīt\n"
        }
    ],
    "synonyms": "kham—the sky; vi-abhram—empty of clouds; udita—arisen; ādityam—with the sun; vāta-varṣam—the wind and rain; ca—and; dāruṇam—fierce; niśamya—seeing; uparatam—ceased; gopān—to the cowherds; govardhana-dharaḥ—the lifter of Govardhana Hill; abravīt—spoke.",
    "translation": "\nSeeing that the fierce wind and rain had now ceased, the sky had become clear of rainclouds, and the sun had risen, Lord Kṛṣṇa, the lifter of Govardhana Hill, spoke to the cowherd community as follows.\n\n",
    "purport": null
}
