{
    "info": {
        "id": "sb/6/15/27",
        "prevId": "sb/6/15/26",
        "nextId": "sb/6/15/28"
    },
    "verses": [
        {
            "roman": "śrī-nārada uvāca\netāṁ mantropaniṣadaṁ\npratīccha prayato mama\nyāṁ dhārayan sapta-rātrād\ndraṣṭā saṅkarṣaṇaṁ vibhum\n"
        }
    ],
    "synonyms": "śrī-nāradaḥ uvāca—Śrī Nārada Muni said; etām—this; mantra-upaniṣadam—Upaniṣad in the form of a mantra by which one can achieve the highest goal of life; pratīccha—accept; prayataḥ—with great attention (after finishing the funeral ceremony of your dead son); mama—from me; yām—which; dhārayan—accepting; sapta-rātrāt—after seven nights; draṣṭā—you will see; saṅkarṣaṇam—the Supreme Personality of Godhead, Saṅkarṣaṇa; vibhum—the Lord.",
    "translation": "\nThe great sage Nārada continued: My dear King, attentively receive from me a mantra, which is most auspicious. After accepting it from me, in seven nights you will be able to see the Lord face to face.\n\n",
    "purport": null
}
