{
    "info": {
        "id": "sb/1/19/38",
        "prevId": "sb/1/19/37",
        "nextId": "sb/1/19/39"
    },
    "verses": [
        {
            "roman": "yac chrotavyam atho japyaṁ\nyat kartavyaṁ nṛbhiḥ prabho\nsmartavyaṁ bhajanīyaṁ vā\nbrūhi yad vā viparyayam\n"
        }
    ],
    "synonyms": "yat—whatever; śrotavyam—worth hearing; atho—thereof; japyam—chanted; yat—what also; kartavyam—executed; nṛbhiḥ—by the people in general; prabho—O master; smartavyam—that which is remembered; bhajanīyam—worshipable; vā—either; brūhi—please explain; yad vā—what it may be; viparyayam—against the principle.",
    "translation": "\nPlease let me know what a man should hear, chant, remember and worship, and also what he should not do. Please explain all this to me.\n\n",
    "purport": null
}
