{
    "info": {
        "id": "sb/9/12/16",
        "prevId": "sb/9/12/15",
        "nextId": "sb/9/13/1"
    },
    "verses": [
        {
            "roman": "ikṣvākūṇām ayaṁ vaṁśaḥ\nsumitrānto bhaviṣyati\nyatas taṁ prāpya rājānaṁ\nsaṁsthāṁ prāpsyati vai kalau\n"
        }
    ],
    "synonyms": "ikṣvākūṇām—of the dynasty of King Ikṣvāku; ayam—this (what has been described); vaṁśaḥ—descendants; sumitra-antaḥ—Sumitra being the last king of this dynasty; bhaviṣyati—will appear in the future, while the Kali-yuga still continues; yataḥ—because; tam—him, Mahārāja Sumitra; prāpya—getting; rājānam—as a king in that dynasty; saṁsthām—culmination; prāpsyati—gets; vai—indeed; kalau—at the end of Kali-yuga.",
    "translation": "The last king in the dynasty of Ikṣvāku will be Sumitra; after Sumitra there will be no more sons in the dynasty of the sun-god, and thus the dynasty will end.",
    "purport": null
}
