{
    "info": {
        "id": "sb/11/31/2-3",
        "prevId": "sb/11/31/1",
        "nextId": "sb/11/31/4"
    },
    "verses": [
        {
            "roman": "pitaraḥ siddha-gandharvā\nvidyādhara-mahoragāḥ\ncāraṇā yakṣa-rakṣāṁsi\nkinnarāpsaraso dvijāḥ\n"
        },
        {
            "roman": "draṣṭu-kāmā bhagavato\nniryāṇaṁ paramotsukāḥ\ngāyantaś ca gṛṇantaś ca\nśaureḥ karmāṇi janma ca\n"
        }
    ],
    "synonyms": "pitaraḥ—the forefathers; siddha-gandharvāḥ—the Siddhas and Gandharvas; vidyādhara-mahā-uragāḥ—the Vidyādharas and the great serpents; cāraṇāḥ—the Cāraṇas; yakṣa-rakṣāṁsi—the Yakṣas and Rākṣasas; kinnara-apsarasaḥ—the Kinnaras and Apsarās; dvijāḥ—the great birds; draṣṭu-kāmāḥ—desirous of seeing; bhagavataḥ—of the Supreme Personality of Godhead; niryāṇam—the passing away; parama-utsukāḥ—very eager; gāyantaḥ—chanting; ca—and; gṛṇantaḥ—praising; ca—and; śaureḥ—of Lord Śauri (Kṛṣṇa); karmāṇi—the activities; janma—the birth; ca—and.",
    "translation": "The forefathers, Siddhas, Gandharvas, Vidyādharas and great serpents also came, along with the Cāraṇas, Yakṣas, Rākṣasas, Kinnaras, Apsarās and relatives of Garuḍa, greatly eager to witness the departure of the Supreme Personality of Godhead. As they were coming, all these personalities variously chanted and glorified the birth and activities of Lord Śauri [Kṛṣṇa].",
    "purport": null
}
