{
    "info": {
        "id": "sb/11/31/27",
        "prevId": "sb/11/31/26",
        "nextId": "sb/11/31/28"
    },
    "verses": [
        {
            "roman": "ya etad deva-devasya\nviṣṇoḥ karmāṇi janma ca\nkīrtayec chraddhayā martyaḥ\nsarva-pāpaiḥ pramucyate\n"
        }
    ],
    "synonyms": "yaḥ—who; etat—these; deva-devasya—of the Lord of lords; viṣṇoḥ—of Lord Viṣṇu; karmāṇi—the activities; janma—the birth; ca—and; kīrtayet—chants; śraddhayā—with faith; martyaḥ—a human being; sarva-pāpaiḥ—from all sins; pramucyate—becomes completely liberated.",
    "translation": "A person who with faith engages in chanting the glories of these various pastimes and incarnations of Viṣṇu, the Lord of lords, will gain liberation from all sins.",
    "purport": null
}
