{
    "info": {
        "id": "sb/11/30/45",
        "prevId": "sb/11/30/44",
        "nextId": "sb/11/30/46"
    },
    "verses": [
        {
            "roman": "tam anvagacchan divyāni\nviṣṇu-praharaṇāni ca\ntenāti-vismitātmānaṁ\nsūtam āha janārdanaḥ\n"
        }
    ],
    "synonyms": "tam—that chariot; anvagacchan—they followed; divyāni—divine; viṣṇu—of Lord Viṣṇu; praharaṇāni—the weapons; ca—and; tena—by that occurrence; ati-vismita—astonished; ātmānam—his mind; sūtam—to the driver; āha—spoke; janārdanaḥ—Lord Śrī Kṛṣṇa.",
    "translation": "\nAll the divine weapons of Viṣṇu rose up and followed the chariot. The Lord, Janārdana, then spoke to His chariot driver, who was most astonished to see all this.\n\n",
    "purport": null
}
